{
  "id": "ding-darling-nwr",
  "name": "J.N. \"Ding\" Darling National Wildlife Refuge",
  "description": "National Wildlife Refuge in FL",
  "location": {
    "lat": 26.4418,
    "lng": -82.1125,
    "state": "FL"
  },
  "geometry": {
    "type": "Polygon",
    "coordinates": [
      [
        [
          -82.08081508595681,
          26.440848825910052
        ],
        [
          -82.08275009823181,
          26.445754711745952
        ],
        [
          -82.0885305061195,
          26.452228986641032
        ],
        [
          -82.09179556671151,
          26.455611503891298
        ],
        [
          -82.10016907212334,
          26.463781604114743
        ],
        [
          -82.10214717108222,
          26.470798434632293
        ],
        [
          -82.11551663510629,
          26.466683673323995
        ],
        [
          -82.11915656152942,
          26.462682841377315
        ],
        [
          -82.12409065901994,
          26.461360489369937
        ],
        [
          -82.13162125284815,
          26.461648294331386
        ],
        [
          -82.14007345173762,
          26.45239258251592
        ],
        [
          -82.14428478641197,
          26.449040068369463
        ],
        [
          -82.13589695534678,
          26.439867716286113
        ],
        [
          -82.14142082415468,
          26.43512206229252
        ],
        [
          -82.13806663956154,
          26.425378373562737
        ],
        [
          -82.13460681046999,
          26.425658320783327
        ],
        [
          -82.12404305962376,
          26.422827803101317
        ],
        [
          -82.11637381845675,
          26.414103326943103
        ],
        [
          -82.11437949733572,
          26.42110304688069
        ],
        [
          -82.10680337678225,
          26.416094138106377
        ],
        [
          -82.09604138993731,
          26.416792585330455
        ],
        [
          -82.09190825551163,
          26.423962328764667
        ],
        [
          -82.0864059250904,
          26.42995736438531
        ],
        [
          -82.08366300259286,
          26.434615890954372
        ],
        [
          -82.08081508595681,
          26.440848825910052
        ]
      ]
    ]
  },
  "area": {
    "acres": 6400,
    "km2": 25.9,
    "hectares": 2589.99
  },
  "designation": "National Wildlife Refuge",
  "metadata": {
    "source": "Conservation Connector Site Inventory",
    "lastUpdated": "2025-10-17",
    "dataQuality": "medium",
    "geometrySource": "Generated approximation based on area and center point",
    "approximateArea": true
  }
}
